[
  {
    "fen": "5a3/2P6/5k3/1C7/6b2/6B2/9/9/9/4K4 w - - 0 1",
    "type": "單炮單低兵單相 vs 單士單象",
    "typeFull": "單炮單低兵單相 vs 單士單象",
    "classification": {
      "type": "單炮單低兵單相 vs 單士單象",
      "typeFull": "單炮單低兵單相 vs 單士單象",
      "redPieces": {
        "C": 1,
        "P": 1,
        "B": 1
      },
      "blackPieces": {
        "a": 1,
        "b": 1
      },
      "totalPieces": 6,
      "pawnAnalysis": {
        "red": {
          "total": 1,
          "low": 1,
          "bottom": 0,
          "normal": 0
        },
        "black": {
          "total": 0,
          "low": 0,
          "bottom": 0,
          "normal": 0
        }
      }
    },
    "result": "egtb:需要查詢",
    "bestMove": "需要查詢",
    "timestamp": "2025-10-25T00:00:00.000Z"
  },
  {
    "fen": "5a3/2P2k3/4b4/1C7/9/6B2/9/9/9/4K4 w - - 0 1",
    "type": "單炮單低兵單相 vs 單士單象",
    "typeFull": "單炮單低兵單相 vs 單士單象",
    "classification": {
      "type": "單炮單低兵單相 vs 單士單象",
      "typeFull": "單炮單低兵單相 vs 單士單象",
      "redPieces": {
        "C": 1,
        "P": 1,
        "B": 1
      },
      "blackPieces": {
        "a": 1,
        "b": 1
      },
      "totalPieces": 6,
      "pawnAnalysis": {
        "red": {
          "total": 1,
          "low": 1,
          "bottom": 0,
          "normal": 0
        },
        "black": {
          "total": 0,
          "low": 0,
          "bottom": 0,
          "normal": 0
        }
      }
    },
    "result": "egtb:需要查詢",
    "bestMove": "需要查詢",
    "timestamp": "2025-10-25T00:00:01.000Z"
  },
  {
    "fen": "2b2a3/2P2k3/9/C8/9/6B2/9/9/9/4K4 w - - 0 1",
    "type": "單炮單低兵單相 vs 單士單象",
    "typeFull": "單炮單低兵單相 vs 單士單象",
    "classification": {
      "type": "單炮單低兵單相 vs 單士單象",
      "typeFull": "單炮單低兵單相 vs 單士單象",
      "redPieces": {
        "C": 1,
        "P": 1,
        "B": 1
      },
      "blackPieces": {
        "a": 1,
        "b": 1
      },
      "totalPieces": 6,
      "pawnAnalysis": {
        "red": {
          "total": 1,
          "low": 1,
          "bottom": 0,
          "normal": 0
        },
        "black": {
          "total": 0,
          "low": 0,
          "bottom": 0,
          "normal": 0
        }
      }
    },
    "result": "egtb:需要查詢",
    "bestMove": "需要查詢",
    "timestamp": "2025-10-25T00:00:02.000Z"
  }
]